partis/pyproj/_incremental.py
partis/pyproj/validate.py
partis/pyproj/pkginfo.py
partis/pyproj/cache.py
partis/pyproj/pep.py
partis/pyproj/norms.py
partis/pyproj/__init__.py
partis/pyproj/file.py
partis/pyproj/pyproj.py
partis/pyproj/pptoml.py
partis/pyproj/load_module.py
partis/pyproj/legacy.py
partis/pyproj/template.py
partis/pyproj/backend.py
partis/pyproj/py.typed
partis/pyproj/_nonprintable.py
partis/pyproj/_legacy_setup.py
partis/pyproj/dist_file/dist_targz.py
partis/pyproj/dist_file/dist_binary.py
partis/pyproj/dist_file/__init__.py
partis/pyproj/dist_file/dist_base.py
partis/pyproj/dist_file/dist_copy.py
partis/pyproj/dist_file/dist_source.py
partis/pyproj/dist_file/dist_zip.py
partis/pyproj/cli/__main__.py
partis/pyproj/cli/init_pyproj.py
partis/pyproj/cli/build_pyproj.py
partis/pyproj/path/pattern.py
partis/pyproj/path/scandir.py
partis/pyproj/path/utils.py
partis/pyproj/path/match.py
partis/pyproj/path/__init__.py
partis/pyproj/builder/__init__.py
partis/pyproj/builder/builder.py
partis/pyproj/builder/download.py
partis/pyproj/builder/process.py
partis/pyproj/builder/meson.py
partis/pyproj/builder/cmake.py
partis_pyproj-0.2.1.dist-info/METADATA
partis_pyproj-0.2.1.dist-info/LICENSE.txt
partis_pyproj-0.2.1.dist-info/top_level.txt
partis_pyproj-0.2.1.dist-info/entry_points.txt
partis_pyproj-0.2.1.dist-info/WHEEL
partis_pyproj-0.2.1.dist-info/RECORD
