Metadata-Version: 2.1
Name: partis-pyproj
Version: 0.2.1
Requires-Python: >=3.8
Author-email: "Nanohmics Inc." <software.support@nanohmics.com>
Maintainer-email: "Nanohmics Inc." <software.support@nanohmics.com>
Summary: Minimal set of Python project utilities (PEP-517/621)
License-File: LICENSE.txt
Project-URL: homepage, https://github.com/kcdodd/partis-pyproj/
Classifier: Operating System :: POSIX :: Linux
Classifier: Programming Language :: Python :: 3
Classifier: Intended Audience :: Developers
Classifier: Programming Language :: Python
Classifier: License :: OSI Approved :: BSD License
Classifier: Development Status :: 4 - Beta
Classifier: Operating System :: Microsoft :: Windows
Classifier: Topic :: Software Development :: Build Tools
Provides-Extra: meson
Provides-Extra: cmake
Requires-Dist: packaging>=24.2
Requires-Dist: tomli>=2.0.1
Requires-Dist: requests>=2.32.3
Requires-Dist: meson>=0.61.3; extra == "meson"
Requires-Dist: ninja>=1.10.2.3; extra == "meson"
Requires-Dist: ninja>=1.10.2.3; extra == "cmake"
Requires-Dist: cmake>=3.24.3; extra == "cmake"
